jmux/__init__.py
jmux/awaitable.py
jmux/decoder.py
jmux/demux.py
jmux/error.py
jmux/helpers.py
jmux/pda.py
jmux/types.py
jmux-0.0.4.dist-info/licenses/LICENSE
jmux-0.0.4.dist-info/METADATA
jmux-0.0.4.dist-info/WHEEL
jmux-0.0.4.dist-info/top_level.txt
jmux-0.0.4.dist-info/RECORD
