Metadata-Version: 2.4
Name: jmux
Version: 0.0.4
Summary: JMux: A Python package for demultiplexing a JSON string into multiple awaitable variables.
Author-email: "Johannes A.I. Unruh" <johannes@unruh.ai>
License: MIT License
Project-URL: Homepage, https://github.com/jaunruh/jmux
Project-URL: Repository, https://github.com/jaunruh/jmux
Keywords: demultiplexer,python,package,json
Classifier: Programming Language :: Python :: 3
Classifier: Operating System :: OS Independent
Requires-Python: >=3.12
License-File: LICENSE
Requires-Dist: anyio>=4.0.0
Requires-Dist: pydantic>=2.0.0
Provides-Extra: test
Requires-Dist: pytest; extra == "test"
Requires-Dist: pytest-anyio; extra == "test"
Provides-Extra: dev
Requires-Dist: ruff; extra == "dev"
Requires-Dist: pytest; extra == "dev"
Requires-Dist: pytest-anyio; extra == "dev"
Requires-Dist: uv; extra == "dev"
Requires-Dist: build; extra == "dev"
Requires-Dist: twine; extra == "dev"
Requires-Dist: setuptools; extra == "dev"
Requires-Dist: setuptools_scm[toml]; extra == "dev"
Dynamic: license-file
